[
  {
    "image": "https://c1.neweggimages.com/ProductImageCompressAll300/14-930-056-V07.jpg",
    "name": "ASRock Radeon RX 6700 XT Challenger D Gaming Graphic Card, 12GB GDDR6 VRAM, AMD RDNA2 (RX6700XT CLD 12G)",
    "rating": "Calificaci\u00f3n:  4.8 sobre 5",
    "link": "https://www.newegg.com/asrock-radeon-rx-6700-xt-rx6700xt-cld-12g/p/N82E16814930056?Item=N82E16814930056",
    "price": "$568.99"
  },
  {
    "image": "https://c1.neweggimages.com/ProductImageCompressAll300/14-126-557-V01.jpg",
    "name": "ASUS Dual GeForce RTX 3050 Video Card DUAL-RTX3050-O8G",
    "rating": "Calificaci\u00f3n:  4.7 sobre 5",
    "link": "https://www.newegg.com/asus-geforce-rtx-3050-dual-rtx3050-o8g/p/N82E16814126557?Item=N82E16814126557",
    "price": "$379.99"
  },
  {
    "image": "https://c1.neweggimages.com/ProductImageCompressAll300/14-126-556-25.jpg",
    "name": "ASUS ROG Strix GeForce RTX 3050 Video Card ROG-STRIX-RTX3050-O8G-GAMING",
    "rating": "Calificaci\u00f3n:  4.8 sobre 5",
    "link": "https://www.newegg.com/asus-geforce-rtx-3050-rog-strix-rtx3050-o8g-gaming/p/N82E16814126556?Item=N82E16814126556",
    "price": "$429.99"
  },
  {
    "image": "https://c1.neweggimages.com/ProductImageCompressAll300/14-126-553-V01.jpg",
    "name": "ASUS Dual Radeon RX 6500 XT Video Card DUAL-RX6500XT-O4G",
    "rating": "Calificaci\u00f3n:  4.3 sobre 5",
    "link": "https://www.newegg.com/asus-radeon-rx-6500-xt-dual-rx6500xt-o4g/p/N82E16814126553?Item=N82E16814126553",
    "price": "$249.99"
  },
  {
    "image": "https://c1.neweggimages.com/ProductImageCompressAll300/14-126-550-V11.jpg",
    "name": "ASUS ROG Strix NVIDIA GeForce RTX 3080 OC Edition Gaming Graphics Card (PCIe 4.0, 12GB GDDR6X, LHR, HDMI 2.1, DisplayPort 1.4a, Axial-tech Fan Design, 2.9-slot, Super Alloy Power II, GPU Tweak II)",
    "rating": "Calificaci\u00f3n:  4.1 sobre 5",
    "link": "https://www.newegg.com/asus-geforce-rtx-3080-rog-strix-rtx3080-o12g-gaming/p/N82E16814126550?Item=N82E16814126550",
    "price": "$1,399.99"
  },
  {
    "image": "https://c1.neweggimages.com/ProductImageCompressAll300/14-932-438-V05.jpg",
    "name": "GIGABYTE Eagle GeForce RTX 3080 Ti Video Card GV-N308TEAGLE OC-12GD",
    "rating": "Calificaci\u00f3n:  3.5 sobre 5",
    "link": "https://www.newegg.com/gigabyte-geforce-rtx-3080-ti-gv-n308teagle-oc-12gd/p/N82E16814932438?Item=N82E16814932438",
    "price": "$1,429.99"
  },
  {
    "image": "https://c1.neweggimages.com/ProductImageCompressAll300/14-932-435-V06.jpg",
    "name": "GIGABYTE AORUS GeForce RTX 3080 Ti Video Card GV-N308TAORUS M-12GD",
    "rating": "Calificaci\u00f3n:  4.5 sobre 5",
    "link": "https://www.newegg.com/gigabyte-geforce-rtx-3080-ti-gv-n308taorus-m-12gd/p/N82E16814932435?Item=N82E16814932435",
    "price": "$1,449.99"
  },
  {
    "image": "https://c1.neweggimages.com/ProductImageCompressAll300/14-932-444-01.jpg",
    "name": "GIGABYTE Eagle GeForce RTX 3070 Ti Video Card GV-N307TEAGLE OC-8GD",
    "rating": "Calificaci\u00f3n:  4.9 sobre 5",
    "link": "https://www.newegg.com/gigabyte-geforce-rtx-3070-ti-gv-n307teagle-oc-8gd/p/N82E16814932444?Item=N82E16814932444",
    "price": "$699.99"
  },
  {
    "image": "https://c1.neweggimages.com/ProductImageCompressAll300/14-126-558-V01.jpg",
    "name": "ASUS Phoenix GeForce RTX 3050 Video Card PH-RTX3050-8G",
    "rating": "Calificaci\u00f3n:  4.7 sobre 5",
    "link": "https://www.newegg.com/asus-geforce-rtx-3050-ph-rtx3050-8g/p/N82E16814126558?Item=N82E16814126558",
    "price": "$299.99"
  },
  {
    "image": "https://c1.neweggimages.com/ProductImageCompressAll300/14-137-656-V01.jpg",
    "name": "MSI Ventus GeForce RTX 3080 Ti Video Card RTX 3080 Ti VENTUS 3X 12G",
    "rating": "Calificaci\u00f3n:  5 sobre 5",
    "link": "https://www.newegg.com/msi-geforce-rtx-3080-ti-rtx-3080-ti-ventus-3x-12g/p/N82E16814137656?Item=N82E16814137656",
    "price": "Out of Stock"
  },
  {
    "image": "https://c1.neweggimages.com/ProductImageCompressAll300/14-487-549-V07.jpg",
    "name": "EVGA GeForce RTX 3080 Ti XC3 GAMING Video Card, 12G-P5-3953-KR, 12GB GDDR6X, iCX3 Cooling, ARGB LED, Metal Backplate",
    "rating": "Calificaci\u00f3n:  5 sobre 5",
    "link": "https://www.newegg.com/evga-geforce-rtx-3080-ti-12g-p5-3953-kr/p/N82E16814487549?Item=N82E16814487549",
    "price": "Out of Stock"
  },
  {
    "image": "https://c1.neweggimages.com/ProductImageCompressAll300/14-126-545-V01.jpg",
    "name": "ASUS Noctua OC Edition GeForce RTX 3070 Video Card RTX3070-O8G-NOCTUA (LHR)",
    "rating": "Calificaci\u00f3n:  5 sobre 5",
    "link": "https://www.newegg.com/asus-geforce-rtx-3070-rtx3070-o8g-noctua/p/N82E16814126545?Item=N82E16814126545",
    "price": "Out of Stock"
  }
]